asyncqlio/__init__.py
asyncqlio/db.py
asyncqlio/exc.py
asyncqlio/meta.py
asyncqlio/sentinels.py
asyncqlio/utils.py
asyncqlio/backends/__init__.py
asyncqlio/backends/base.py
asyncqlio/backends/mysql/__init__.py
asyncqlio/backends/mysql/aiomysql.py
asyncqlio/backends/postgresql/__init__.py
asyncqlio/backends/postgresql/asyncpg.py
asyncqlio/backends/sqlite3/__init__.py
asyncqlio/backends/sqlite3/sqlite3.py
asyncqlio/orm/__init__.py
asyncqlio/orm/inspection.py
asyncqlio/orm/operators.py
asyncqlio/orm/query.py
asyncqlio/orm/session.py
asyncqlio/orm/ddl/__init__.py
asyncqlio/orm/ddl/migration_tool.py
asyncqlio/orm/schema/__init__.py
asyncqlio/orm/schema/column.py
asyncqlio/orm/schema/decorators.py
asyncqlio/orm/schema/relationship.py
asyncqlio/orm/schema/table.py
asyncqlio/orm/schema/types.py
asyncqlio-0.1.0.1.dist-info/DESCRIPTION.rst
asyncqlio-0.1.0.1.dist-info/METADATA
asyncqlio-0.1.0.1.dist-info/RECORD
asyncqlio-0.1.0.1.dist-info/WHEEL
asyncqlio-0.1.0.1.dist-info/entry_points.txt
asyncqlio-0.1.0.1.dist-info/metadata.json
asyncqlio-0.1.0.1.dist-info/top_level.txt
