Metadata-Version: 2.0
Name: asyncqlio
Version: 0.1.0.1
Summary: An asyncio ORM for Python 3.5+
Home-page: https://github.com/SunDwarf/asyncqlio
Author: Laura Dickinson
Author-email: l@veriny.tf
License: MIT
Platform: UNKNOWN
Requires-Python: >=3.5.2
Requires-Dist: cached-property (==1.3.0)
Requires-Dist: asyncio-extras (==1.3.0)
Provides-Extra: docs
Requires-Dist: sphinx (>=1.5.0); extra == 'docs'
Requires-Dist: sphinxcontrib-asyncio; extra == 'docs'
Requires-Dist: guzzle-sphinx-theme; extra == 'docs'
Provides-Extra: mysql
Requires-Dist: aiomysql (>=0.0.9); extra == 'mysql'
Provides-Extra: postgresql
Requires-Dist: asyncpg (>=0.12.0); extra == 'postgresql'
